ascii_moon_phase/__init__.py
ascii_moon_phase/__main__.py
ascii_moon_phase-0.3.0.dist-info/METADATA
ascii_moon_phase-0.3.0.dist-info/WHEEL
ascii_moon_phase-0.3.0.dist-info/entry_points.txt
ascii_moon_phase-0.3.0.dist-info/licenses/LICENSE
ascii_moon_phase-0.3.0.dist-info/RECORD
