Metadata-Version: 2.4
Name: ascii_moon_phase
Version: 0.3.0
Summary: Display the current lunar phase as ASCII art.
Project-URL: Homepage, https://github.com/asweigart/ascii-moon-phase-python
Project-URL: Issues, https://github.com/asweigart/ascii-moon-phase-python/issues
Author-email: Al Sweigart <al@inventwithpython.com>
License: Copyright 2025 Al Sweigart
License-File: LICENSE
Keywords: art,ascii,lunar,moon,phase,terminal
Classifier: Environment :: Console
Classifier: Programming Language :: Python :: 3
Classifier: Topic :: Software Development :: Libraries :: Python Modules
Classifier: Topic :: Terminals
Requires-Python: >=3.6
